msQ/__init__.py
msQ-0.1.0.dev0.dist-info/METADATA
msQ-0.1.0.dev0.dist-info/WHEEL
msQ-0.1.0.dev0.dist-info/top_level.txt
msQ-0.1.0.dev0.dist-info/RECORD
